.bumpversion.cfg
CHANGELOG.md
CONTRIBUTING.md
DEVELOPMENT_GUIDE.md
LICENSE
MANIFEST.in
README.md
RELEASING.md
pyproject.toml
pytest.ini
requirements-azure.txt
requirements-dev.txt
requirements-gcs.txt
requirements-s3.txt
requirements.txt
setup.cfg
setup.py
tox.ini
docs/Makefile
docs/UPDATE.md
docs/conf.py
docs/extending-developing.rst
docs/extending-entry-points.rst
docs/extending-overview.rst
docs/index.rst
docs/installation.rst
docs/make.bat
docs/requirements-doc.txt
docs/troubleshooting.rst
docs/usage-cli.rst
docs/usage-execute.rst
docs/usage-parameterize.rst
docs/usage-store.rst
docs/usage-workflow.rst
docs/_static/custom.css
docs/_static/images/papermill.png
docs/_templates/navigation.html
docs/_templates/page.html
docs/_templates/relations.html
docs/img/custom_execution_engine.png
docs/img/enable_parameters.gif
docs/img/matplotlib_hist.png
docs/img/nb_dataframe.png
docs/img/nbs_dataframe.png
docs/img/parameters.png
docs/reference/index.rst
docs/reference/papermill-cli.rst
docs/reference/papermill-io.rst
docs/reference/papermill-storage.rst
docs/reference/papermill-translators.rst
docs/reference/papermill-utilities.rst
docs/reference/papermill-workflow.rst
docs/reference/papermill.tests.rst
papermill/__init__.py
papermill/abs.py
papermill/adl.py
papermill/cli.py
papermill/engines.py
papermill/exceptions.py
papermill/execute.py
papermill/iorw.py
papermill/log.py
papermill/parameterize.py
papermill/preprocess.py
papermill/s3.py
papermill/translators.py
papermill/utils.py
papermill/version.py
papermill/tests/__init__.py
papermill/tests/test_abs.py
papermill/tests/test_adl.py
papermill/tests/test_cli.py
papermill/tests/test_conf.py
papermill/tests/test_engines.py
papermill/tests/test_exceptions.py
papermill/tests/test_execute.py
papermill/tests/test_gcs.py
papermill/tests/test_iorw.py
papermill/tests/test_parameterize.py
papermill/tests/test_preprocessor.py
papermill/tests/test_s3.py
papermill/tests/test_translators.py
papermill/tests/test_utils.py
papermill_nb_runner.egg-info/PKG-INFO
papermill_nb_runner.egg-info/SOURCES.txt
papermill_nb_runner.egg-info/dependency_links.txt
papermill_nb_runner.egg-info/entry_points.txt
papermill_nb_runner.egg-info/requires.txt
papermill_nb_runner.egg-info/top_level.txt