Metadata-Version: 2.1
Name: papermill-nb-runner
Version: 1.1.9
Summary: Use papermill in CI/CD.
Home-page: https://github.com/nteract/papermill
Author: Yash
Author-email: yashanantha@outlook.com
License: BSD
Project-URL: Documentation, https://papermill.readthedocs.io
Project-URL: Funding, https://nteract.io
Project-URL: Source, https://github.com/nteract/papermill/
Project-URL: Tracker, https://github.com/nteract/papermill/issues
Keywords: jupyter mapreduce nteract pipeline notebook
Platform: UNKNOWN
Classifier: Intended Audience :: Developers
Classifier: Intended Audience :: System Administrators
Classifier: Intended Audience :: Science/Research
Classifier: License :: OSI Approved :: BSD License
Classifier: Programming Language :: Python
Classifier: Programming Language :: Python :: 3
Classifier: Programming Language :: Python :: 2.7
Provides-Extra: dev
Provides-Extra: test
Provides-Extra: all
Provides-Extra: gcs
Provides-Extra: s3
Provides-Extra: azure
